social_b_matching/__init__.py
social_b_matching/b_matching.py
social_b_matching-0.0.1.dist-info/LICENSE
social_b_matching-0.0.1.dist-info/WHEEL
social_b_matching-0.0.1.dist-info/METADATA
social_b_matching-0.0.1.dist-info/RECORD
