Metadata-Version: 2.1
Name: social_b_matching
Version: 0.0.1
Summary: Optimal b-matching for scored meeting assignments.
Keywords: 
Author-email: Dan Goldman <danbgoldman@gmail.com>
Requires-Python: >=3.8
Classifier: Programming Language :: Python :: 3
Classifier: License :: OSI Approved :: Apache Software License
Classifier: Operating System :: OS Independent
Classifier: Topic :: Office/Business :: Scheduling
Requires-Dist: absl-py
Requires-Dist: ortools
Provides-Extra: dev
